INSTALL
LICENSE.txt
MANIFEST.in
README.md
RELEASE-NOTES
THANKS
references.json
requirements.txt
setup.cfg
setup.py
scholarec/VERSION
scholarec/__init__.py
scholarec/__main__.py
scholarec.egg-info/PKG-INFO
scholarec.egg-info/SOURCES.txt
scholarec.egg-info/dependency_links.txt
scholarec.egg-info/not-zip-safe
scholarec.egg-info/requires.txt
scholarec.egg-info/top_level.txt
scholarec/base/__init__.py
scholarec/base/arxiv.py
scholarec/base/operations.py
scholarec/handlers/__init__.py
scholarec/handlers/datahandler.py