Metadata-Version: 1.1
Name: scholarec
Version: 1.0.1
Summary: Recommendation engine for scholarly works
Home-page: https://github.com/arcolife/scholarec
Author: Archit Sharma
Author-email: archit.py@gmail.com
License: GPL v3
Keywords: python ArXiv API recommendation
Platform: UNKNOWN
Classifier: Development Status :: 3 - Alpha
Classifier: Topic :: Software Development :: Libraries
Classifier: License :: OSI Approved :: GNU General Public License v3 (GPLv3)
Classifier: Programming Language :: Python
Classifier: Intended Audience :: End Users/Desktop
Classifier: Intended Audience :: Developers
